{
  "$schema": "http://cyclonedx.org/schema/bom-1.4.schema.json",
  "bomFormat": "CycloneDX",
  "specVersion": "1.4",
  "serialNumber": "urn:uuid:5ee7de78-2218-4a01-8234-a0813a223132",
  "version": 1,
  "metadata": {
    "timestamp": "2023-08-16T06:48:27.485617+00:00",
    "tools": [
      {
        "vendor": "CycloneDX",
        "name": "cyclonedx-bom",
        "version": "3.11.2"
      },
      {
        "vendor": "CycloneDX",
        "name": "cyclonedx-python-lib",
        "version": "3.1.5",
        "externalReferences": [
          {
            "url": "https://github.com/CycloneDX/cyclonedx-python-lib/actions",
            "type": "build-system"
          },
          {
            "url": "https://pypi.org/project/cyclonedx-python-lib/",
            "type": "distribution"
          },
          {
            "url": "https://cyclonedx.github.io/cyclonedx-python-lib/",
            "type": "documentation"
          },
          {
            "url": "https://github.com/CycloneDX/cyclonedx-python-lib/issues",
            "type": "issue-tracker"
          },
          {
            "url": "https://github.com/CycloneDX/cyclonedx-python-lib/blob/main/LICENSE",
            "type": "license"
          },
          {
            "url": "https://github.com/CycloneDX/cyclonedx-python-lib/blob/main/CHANGELOG.md",
            "type": "release-notes"
          },
          {
            "url": "https://github.com/CycloneDX/cyclonedx-python-lib",
            "type": "vcs"
          },
          {
            "url": "https://cyclonedx.org",
            "type": "website"
          }
        ]
      }
    ]
  },
  "components": [
    {
      "type": "library",
      "bom-ref": "2546540f-900e-48bf-b19e-db80e5989170",
      "name": "PyYAML",
      "version": "6.0.1",
      "purl": "pkg:pypi/pyyaml@6.0.1"
    },
    {
      "type": "library",
      "bom-ref": "557f82e7-6124-41df-9845-258066b164f7",
      "name": "lxml",
      "version": "4.9.3",
      "purl": "pkg:pypi/lxml@4.9.3"
    },
    {
      "type": "library",
      "bom-ref": "6745fceb-e7ed-4e09-9431-6b2536137f66",
      "name": "msgspec",
      "version": "0.18.0",
      "purl": "pkg:pypi/msgspec@0.18.0"
    },
    {
      "type": "library",
      "bom-ref": "fd831d18-f131-4044-9b84-c99b044c795a",
      "name": "psutil",
      "version": "5.9.5",
      "purl": "pkg:pypi/psutil@5.9.5"
    },
    {
      "type": "library",
      "bom-ref": "cc3178be-2856-430e-81f1-3a99d0a5baad",
      "name": "py-cpuinfo",
      "version": "9.0.0",
      "purl": "pkg:pypi/py-cpuinfo@9.0.0"
    }
  ],
  "dependencies": [
    {
      "ref": "2546540f-900e-48bf-b19e-db80e5989170",
      "dependsOn": []
    },
    {
      "ref": "557f82e7-6124-41df-9845-258066b164f7",
      "dependsOn": []
    },
    {
      "ref": "6745fceb-e7ed-4e09-9431-6b2536137f66",
      "dependsOn": []
    },
    {
      "ref": "fd831d18-f131-4044-9b84-c99b044c795a",
      "dependsOn": []
    },
    {
      "ref": "cc3178be-2856-430e-81f1-3a99d0a5baad",
      "dependsOn": []
    }
  ]
}
